rvid/__init__.py
rvid/core.py
rvid-0.1.3.dist-info/LICENSE
rvid-0.1.3.dist-info/METADATA
rvid-0.1.3.dist-info/WHEEL
rvid-0.1.3.dist-info/top_level.txt
rvid-0.1.3.dist-info/RECORD
