Metadata-Version: 2.1
Name: rvid
Version: 0.1.3
Summary: A small package to replace values in dict on python
Home-page: https://github.com/ashnoa/replace-value-in-python-dict
Author: Hiroki Asano
Author-email: asano.hiroki@gmail.com
License: MIT License
